vivisection/__init__.py
vivisection/analyze.py
vivisection/demangle.py
vivisection/emulation.py
vivisection/emutils.py
vivisection/errno.py
vivisection/example_func_setup.py
vivisection/malware.py
vivisection/recon.py
vivisection/viv_plugin/__init__.py
vivisection/viv_plugin/emuclient.py
vivisection/viv_plugin/plugin.py
vivisection/viv_plugin/share.py
vivisection-1.0.1.data/scripts/launchVivisectION
vivisection-1.0.1.data/scripts/vivisection_activate
vivisection-1.0.1.data/scripts/vivisection_deactivate
vivisection-1.0.1.dist-info/LICENSE
vivisection-1.0.1.dist-info/METADATA
vivisection-1.0.1.dist-info/WHEEL
vivisection-1.0.1.dist-info/top_level.txt
vivisection-1.0.1.dist-info/RECORD
