Metadata-Version: 2.1
Name: vivisection
Version: 1.0.1
Summary: # VivisectION Emulation-Driven Reversing Toolset
Home-page: https://github.com/atlas0fd00m/VivisectION
Download-URL: https://github.com/atlas0fd00m/VivisectION/archive/v1.0.1.tar.gz
Author: atlas of d00m
Author-email: atlas@r4780y.com
License-File: LICENSE
Requires-Dist: vivisect >=1.0.8
